pytypedmatrix/__init__.py
pytypedmatrix/exceptions/__init__.py
pytypedmatrix/exceptions/matrix_error.py
pytypedmatrix/generics.py
pytypedmatrix/square_matrix.py
pytypedmatrix-0.1.0.dist-info/LICENSE
pytypedmatrix-0.1.0.dist-info/METADATA
pytypedmatrix-0.1.0.dist-info/WHEEL
pytypedmatrix-0.1.0.dist-info/RECORD
